mdast_cli/__init__.py
mdast_cli/mdast_scan.py
mdast_cli/distribution_systems/__init__.py
mdast_cli/distribution_systems/appstore.py
mdast_cli/distribution_systems/base.py
mdast_cli/distribution_systems/google_play.py
mdast_cli/distribution_systems/appstore_client/__init__.py
mdast_cli/distribution_systems/appstore_client/store.py
mdast_cli/distribution_systems/appstore_client/schemas/__init__.py
mdast_cli/distribution_systems/appstore_client/schemas/store_authenticate_req.py
mdast_cli/distribution_systems/appstore_client/schemas/store_authenticate_resp.py
mdast_cli/distribution_systems/appstore_client/schemas/store_buyproduct_req.py
mdast_cli/distribution_systems/appstore_client/schemas/store_buyproduct_resp.py
mdast_cli/distribution_systems/appstore_client/schemas/store_download_req.py
mdast_cli/distribution_systems/appstore_client/schemas/store_download_resp.py
mdast_cli/distribution_systems/gpapi/__init__.py
mdast_cli/distribution_systems/gpapi/config.py
mdast_cli/distribution_systems/gpapi/device.properties
mdast_cli/distribution_systems/gpapi/googleplay.py
mdast_cli/distribution_systems/gpapi/googleplay_pb2.py
mdast_cli/distribution_systems/gpapi/utils.py
mdast_cli/helpers/__init__.py
mdast_cli/helpers/const.py
mdast_cli/helpers/helpers.py
mdast_cli/helpers/logging.py
poly_app_downloader-1.3.14.dist-info/METADATA
poly_app_downloader-1.3.14.dist-info/WHEEL
poly_app_downloader-1.3.14.dist-info/entry_points.txt
poly_app_downloader-1.3.14.dist-info/top_level.txt
poly_app_downloader-1.3.14.dist-info/RECORD
