Metadata-Version: 2.1
Name: poly-app-downloader
Version: 1.3.14
Summary: app_downloader
Home-page: https://github.com/npinaev/poly_app_downloader
Author: npinaev
Classifier: Programming Language :: Python :: 3.9
Classifier: License :: OSI Approved :: MIT License
Classifier: Operating System :: Unix
Requires-Dist: beautifulsoup4 (==4.10.0)
Requires-Dist: cachetools (==5.0.0)
Requires-Dist: certifi (==2021.10.8)
Requires-Dist: cffi (==1.15.0)
Requires-Dist: chardet (==3.0.4)
Requires-Dist: charset-normalizer (==2.0.12)
Requires-Dist: cryptography (==36.0.1)
Requires-Dist: google (==3.0.0)
Requires-Dist: google-api-core (==2.7.0)
Requires-Dist: google-api-python-client (==2.39.0)
Requires-Dist: google-auth (==2.6.0)
Requires-Dist: google-auth-httplib2 (==0.1.0)
Requires-Dist: googleapis-common-protos (==1.55.0)
Requires-Dist: httplib2 (==0.20.4)
Requires-Dist: idna (==2.7)
Requires-Dist: protobuf (==3.19.4)
Requires-Dist: pyasn1 (==0.4.8)
Requires-Dist: pyasn1-modules (==0.2.8)
Requires-Dist: pycparser (==2.21)
Requires-Dist: pyparsing (==3.0.7)
Requires-Dist: requests (==2.27.1)
Requires-Dist: rsa (==4.8)
Requires-Dist: six (==1.16.0)
Requires-Dist: soupsieve (==2.3.1)
Requires-Dist: uritemplate (==4.1.1)
Requires-Dist: urllib3 (==1.26.0)
Requires-Dist: pytest (==7.1.2)
